{"pic":[
{"url":"img/ir/1190.jpg","longitude":"5.13144565594","latitude":"54.767022457"},
{"url":"img/ir/12.jpg","longitude":"41.2649411435","latitude":"9.83302248297"},
{"url":"img/ir/1208.jpg","longitude":"30.7303518221","latitude":"50.5655590156"},
{"url":"img/ir/1216.jpg","longitude":"12.3169096988","latitude":"1.5387219595"},
{"url":"img/ir/1231.jpg","longitude":"32.2434869018","latitude":"28.5443127977"},
{"url":"img/ir/1234.jpg","longitude":"53.1511717143","latitude":"32.913370303"},
{"url":"img/ir/1240.jpg","longitude":"20.2620394105","latitude":"28.4648456314"},
{"url":"img/ir/1258.jpg","longitude":"36.8766627803","latitude":"34.9456629698"},
{"url":"img/ir/1279.jpg","longitude":"23.4735349339","latitude":"48.8439069795"},
{"url":"img/ir/1293.jpg","longitude":"48.2885276111","latitude":"58.4931646377"},
{"url":"img/ir/1301.jpg","longitude":"51.7606009859","latitude":"4.715504882"},
{"url":"img/ir/1325.jpg","longitude":"12.3940260667","latitude":"19.1533269457"},
{"url":"img/ir/133.jpg","longitude":"57.352193887","latitude":"41.6221158186"},
{"url":"img/ir/134.jpg","longitude":"55.4573608808","latitude":"7.18991007839"},
{"url":"img/ir/1353.jpg","longitude":"9.7379424831","latitude":"29.3152640853"},
{"url":"img/ir/1374.jpg","longitude":"12.6187748454","latitude":"42.0405695357"},
{"url":"img/ir/1396.jpg","longitude":"10.4812954782","latitude":"29.3464921912"},
{"url":"img/ir/1400.jpg","longitude":"16.912724039","latitude":"49.3069559655"}
]}