{"pic":[
{"url":"img/ir/6860.jpg","longitude":"32.207854698","latitude":"54.9565660985"},
{"url":"img/ir/6863.jpg","longitude":"7.90034217284","latitude":"35.1717039008"},
{"url":"img/ir/6899.jpg","longitude":"55.3862184029","latitude":"2.29971269306"},
{"url":"img/ir/6917.jpg","longitude":"23.4847013483","latitude":"27.3545894603"},
{"url":"img/ir/6928.jpg","longitude":"53.9904531957","latitude":"38.547623633"},
{"url":"img/ir/6954.jpg","longitude":"13.732848068","latitude":"53.4738569355"},
{"url":"img/ir/6963.jpg","longitude":"26.0984059979","latitude":"5.00811920435"},
{"url":"img/ir/6969.jpg","longitude":"3.71952065719","latitude":"12.5390533424"},
{"url":"img/ir/6983.jpg","longitude":"20.2786030663","latitude":"1.74262212893"},
{"url":"img/ir/7000.jpg","longitude":"42.2317752446","latitude":"30.6655530819"},
{"url":"img/ir/7009.jpg","longitude":"5.18222448881","latitude":"45.2501841254"},
{"url":"img/ir/7039.jpg","longitude":"47.4159781822","latitude":"51.8924465985"},
{"url":"img/ir/7061.jpg","longitude":"41.6955388225","latitude":"22.6718282462"},
{"url":"img/ir/7085.jpg","longitude":"38.1308123602","latitude":"36.9414804746"},
{"url":"img/ir/7090.jpg","longitude":"19.9228739894","latitude":"8.7753305206"},
{"url":"img/ir/7113.jpg","longitude":"30.3472736059","latitude":"52.4586271217"},
{"url":"img/ir/7153.jpg","longitude":"16.9368002363","latitude":"1.12835651455"},
{"url":"img/ir/7183.jpg","longitude":"18.6624434589","latitude":"15.8330731065"}
]}